scaledp/README.md
scaledp/__init__.py
scaledp/enums.py
scaledp/image/DataToImage.py
scaledp/image/ImageCropBoxes.py
scaledp/image/ImageDrawBoxes.py
scaledp/image/__init__.py
scaledp/langs.py
scaledp/metrics/__init__.py
scaledp/metrics/object_similarity.py
scaledp/models/__init__.py
scaledp/models/detectors/BaseDetector.py
scaledp/models/detectors/CraftTextDetector.py
scaledp/models/detectors/DBNetOnnxDetector.py
scaledp/models/detectors/DocTRTextDetector.py
scaledp/models/detectors/FaceDetector.py
scaledp/models/detectors/FastTextDetector.py
scaledp/models/detectors/HasDetectLineOrientation.py
scaledp/models/detectors/LayoutDetector.py
scaledp/models/detectors/SignatureDetector.py
scaledp/models/detectors/YoloDetector.py
scaledp/models/detectors/YoloOnnxDetector.py
scaledp/models/detectors/YoloOnnxTextDetector.py
scaledp/models/detectors/__init__.py
scaledp/models/detectors/craft/__init__.py
scaledp/models/detectors/craft/models.py
scaledp/models/detectors/paddle_onnx/__init__.py
scaledp/models/detectors/paddle_onnx/db_postprocess.py
scaledp/models/detectors/paddle_onnx/imaug.py
scaledp/models/detectors/paddle_onnx/operators.py
scaledp/models/detectors/paddle_onnx/predict_base.py
scaledp/models/detectors/paddle_onnx/predict_det.py
scaledp/models/detectors/yolo/__init__.py
scaledp/models/detectors/yolo/utils.py
scaledp/models/detectors/yolo/yolo.py
scaledp/models/embeddings/BaseEmbeddings.py
scaledp/models/embeddings/TextEmbeddings.py
scaledp/models/embeddings/__init__.py
scaledp/models/extractors/BaseExtractor.py
scaledp/models/extractors/BaseVisualExtractor.py
scaledp/models/extractors/DSPyExtractor.py
scaledp/models/extractors/GeminiVisualExtractor.py
scaledp/models/extractors/LLMExtractor.py
scaledp/models/extractors/LLMVisualExtractor.py
scaledp/models/extractors/__init__.py
scaledp/models/ner/BaseNer.py
scaledp/models/ner/LLMNer.py
scaledp/models/ner/Ner.py
scaledp/models/ner/__init__.py
scaledp/models/recognizers/BaseOcr.py
scaledp-0.2.6.dist-info/LICENSE
scaledp-0.2.6.dist-info/METADATA
scaledp-0.2.6.dist-info/WHEEL
scaledp-0.2.6.dist-info/RECORD
