Metadata-Version: 2.3
Name: scaledp
Version: 0.2.6
Summary: ScaleDP is a library for processing documents and images using Apache Spark and LLMs
License: AGPL-3.0
Author: Mykola Melnyk
Author-email: mykola@stabrise.com
Requires-Python: >=3.10,<4.0
Classifier: License :: OSI Approved :: GNU Affero General Public License v3
Classifier: Programming Language :: Python :: 3
Classifier: Programming Language :: Python :: 3.10
Classifier: Programming Language :: Python :: 3.11
Classifier: Programming Language :: Python :: 3.12
Classifier: Programming Language :: Python :: 3.13
Provides-Extra: llm
Provides-Extra: ml
Provides-Extra: ocr
Provides-Extra: paddle
Requires-Dist: PyMuPDF (==1.24.11)
Requires-Dist: easyocr (==1.7.2) ; extra == "ocr"
Requires-Dist: filelock
Requires-Dist: huggingface-hub (>=0.35.3,<0.36.0)
Requires-Dist: imagesize (==1.4.1)
Requires-Dist: img2pdf (>=0.6.1,<0.7.0)
Requires-Dist: levenshtein (>=0.27.1,<0.28.0)
Requires-Dist: numpy (>=2.2.6,<3.0.0)
Requires-Dist: onnxruntime (==1.22.0)
Requires-Dist: openai (>=1.58.0)
Requires-Dist: opencv-python (>=4.12.0.88,<5.0.0.0)
Requires-Dist: pandas (>=2.3.3,<3.0.0)
Requires-Dist: pillow (>=10.4.0,<11.0.0)
Requires-Dist: pyarrow (>=17.0.0)
Requires-Dist: pyclipper (>=1.3.0.post6,<2.0.0)
Requires-Dist: pydantic (>=1.8.0)
Requires-Dist: pyspark (==3.5.5)
Requires-Dist: pytesseract (==0.3.13)
Requires-Dist: pytest (>=7.4.4,<8.0.0)
Requires-Dist: python-doctr (==0.10.0) ; extra == "ocr"
Requires-Dist: sentence-transformers (>=5.1.2,<6.0.0) ; extra == "ml"
Requires-Dist: shapely (>=2.1.1,<3.0.0)
Requires-Dist: sparkdantic (>=2.6.0,<3.0.0)
Requires-Dist: surya-ocr (==0.8.1) ; extra == "ocr"
Requires-Dist: tenacity (>=8.2.3)
Requires-Dist: torch (==2.4.1) ; (sys_platform == "darwin") and (extra == "ml")
Requires-Dist: torch (>=2.4.1) ; (sys_platform != "darwin") and (extra == "ml")
Requires-Dist: torchvision (>=0.18.0) ; (sys_platform != "darwin") and (extra == "ml")
Requires-Dist: torchvision (>=0.18.0) ; (sys_platform == "darwin") and (extra == "ml")
Requires-Dist: transformers (>=4.36.0,<5.0.0) ; extra == "ml"
Project-URL: Homepage, https://stabrise.com/scaledp/
Project-URL: Repository, https://github.com/StabRise/scaledp
